load_environ_typed/__init__.py
load_environ_typed/_logfmt.py
load_environ_typed/loaders.py
load_environ_typed/py.typed
load_environ_typed-0.3.0.dist-info/METADATA
load_environ_typed-0.3.0.dist-info/WHEEL
load_environ_typed-0.3.0.dist-info/licenses/LICENSE.txt
load_environ_typed-0.3.0.dist-info/RECORD
