Metadata-Version: 2.3
Name: load-environ-typed
Version: 0.3.0
Summary: You define a class, we load it up from environment in a type safe way
Project-URL: Homepage, https://github.com/jbwdevries/python-load-environ-typed
Project-URL: Bug Tracker, https://github.com/jbwdevries/python-load-environ-typed/issues
Author: Johan B.W. de Vries
License: Copyright (c) 2023, Johan B.W. de Vries
License-File: LICENSE.txt
Classifier: License :: OSI Approved :: MIT License
Classifier: Operating System :: OS Independent
Classifier: Programming Language :: Python :: 3
Requires-Python: >=3.8
